lae/__init__.py
lae/train.py
lae-0.0.1.dist-info/METADATA
lae-0.0.1.dist-info/WHEEL
lae-0.0.1.dist-info/top_level.txt
lae-0.0.1.dist-info/RECORD
